Classfile /C:/Users/jayar/dev/personal/code_embedding/test/test4.class
  Last modified 29-May-2021; size 394 bytes
  SHA-256 checksum 0d02b50d8f678a6c714d2bff3af0fc90339d2d47af23b211f80a77a07c2d716a
  Compiled from "test4.java"
class test4
  minor version: 0
  major version: 60
  flags: (0x0020) ACC_SUPER
  this_class: #14                         // test4
  super_class: #2                         // java/lang/Object
  interfaces: 0, fields: 0, methods: 3, attributes: 1
Constant pool:
   #1 = Methodref          #2.#3          // java/lang/Object."<init>":()V
   #2 = Class              #4             // java/lang/Object
   #3 = NameAndType        #5:#6          // "<init>":()V
   #4 = Utf8               java/lang/Object
   #5 = Utf8               <init>
   #6 = Utf8               ()V
   #7 = Class              #8             // test2
   #8 = Utf8               test2
   #9 = Methodref          #7.#3          // test2."<init>":()V
  #10 = Methodref          #7.#11         // test2.n:(I)I
  #11 = NameAndType        #12:#13        // n:(I)I
  #12 = Utf8               n
  #13 = Utf8               (I)I
  #14 = Class              #15            // test4
  #15 = Utf8               test4
  #16 = Utf8               Code
  #17 = Utf8               LineNumberTable
  #18 = Utf8               mn
  #19 = Utf8               m
  #20 = Utf8               StackMapTable
  #21 = Utf8               SourceFile
  #22 = Utf8               test4.java
{
  test4();
    descriptor: ()V
    flags: (0x0000)
    Code:
      stack=1, locals=1, args_size=1
         0: aload_0
         1: invokespecial #1                  // Method java/lang/Object."<init>":()V
         4: return
      LineNumberTable:
        line 2: 0

  int mn(int);
    descriptor: (I)I
    flags: (0x0000)
    Code:
      stack=2, locals=2, args_size=2
         0: iload_1
         1: iconst_3
         2: imul
         3: ireturn
      LineNumberTable:
        line 4: 0

  public int m(int);
    descriptor: (I)I
    flags: (0x0001) ACC_PUBLIC
    Code:
      stack=2, locals=4, args_size=2
         0: iconst_0
         1: istore_2
         2: iload_1
         3: iconst_3
         4: iadd
         5: istore_1
         6: iinc          2, 1
         9: iload_2
        10: iconst_3
        11: if_icmple     2
        14: goto          17
        17: new           #7                  // class test2
        20: dup
        21: invokespecial #9                  // Method test2."<init>":()V
        24: astore_3
        25: aload_3
        26: iload_1
        27: invokevirtual #10                 // Method test2.n:(I)I
        30: ireturn
      LineNumberTable:
        line 7: 0
        line 9: 2
        line 10: 6
        line 11: 9
        line 12: 14
        line 15: 17
        line 16: 25
      StackMapTable: number_of_entries = 2
        frame_type = 252 /* append */
          offset_delta = 2
          locals = [ int ]
        frame_type = 14 /* same */
}
SourceFile: "test4.java"
